LICENSE
MANIFEST.in
README.rst
setup.py
django_paloma.egg-info/PKG-INFO
django_paloma.egg-info/SOURCES.txt
django_paloma.egg-info/dependency_links.txt
django_paloma.egg-info/requires.txt
django_paloma.egg-info/top_level.txt
django_paloma.egg-info/zip-safe
paloma/__init__.py
paloma/models.py