Metadata-Version: 1.0
Name: django-paloma
Version: 1.0.1
Summary: Class based e-mails for Django
Home-page: http://bruun.co/
Author: Nick Bruun
Author-email: nick@bruun.co
License: Copyright 2013 Nick Bruun <nick@bruun.co>
